sql_connector_mcp/__init__.py
sql_connector_mcp/server.py
sql_connector_mcp-0.1.0.dist-info/METADATA
sql_connector_mcp-0.1.0.dist-info/WHEEL
sql_connector_mcp-0.1.0.dist-info/top_level.txt
sql_connector_mcp-0.1.0.dist-info/RECORD
