Metadata-Version: 2.4
Name: sql-connector-mcp
Version: 0.1.0
Summary: An MCP server for SQL database connectivity
Author: Battula Anil Kumar
Author-email: anilkumarbaatula@gmail.com
Classifier: Programming Language :: Python :: 3
Classifier: License :: OSI Approved :: MIT License
Requires-Python: >=3.7
Requires-Dist: sqlalchemy
Requires-Dist: pymysql
Requires-Dist: fastmcp
Dynamic: author
Dynamic: author-email
Dynamic: classifier
Dynamic: description-content-type
Dynamic: requires-dist
Dynamic: requires-python
Dynamic: summary
